pymfdata/__init__.py
pymfdata/common/__init__.py
pymfdata/common/usecase.py
pymfdata/mongodb/__init__.py
pymfdata/mongodb/connection.py
pymfdata/mongodb/repository.py
pymfdata/rdb/__init__.py
pymfdata/rdb/connection.py
pymfdata/rdb/mapper.py
pymfdata/rdb/migration.py
pymfdata/rdb/repository.py
pymfdata/rdb/transaction.py
pymfdata/rdb/usecase.py
python_mf_data-0.2.6.dist-info/WHEEL
python_mf_data-0.2.6.dist-info/METADATA
python_mf_data-0.2.6.dist-info/RECORD
