Metadata-Version: 2.1
Name: python-mf-data
Version: 0.2.6
Summary: Python Micro Framework Data
Home-page: https://github.com/NEONKID/python-mf-data
Author: Neon K.I.D
Author-email: contact@neonkid.xyz
Requires-Python: >=3.8,<4.0
Classifier: Programming Language :: Python :: 3
Classifier: Programming Language :: Python :: 3.10
Classifier: Programming Language :: Python :: 3.8
Classifier: Programming Language :: Python :: 3.9
Provides-Extra: mongodb
Provides-Extra: rdb
Requires-Dist: SQLAlchemy[asyncio] (>=1.4.28,<2.0.0); extra == "rdb"
Requires-Dist: alembic (>=1.7.5,<2.0.0); extra == "rdb"
Requires-Dist: asyncio (>=3.4.3,<4.0.0)
Requires-Dist: motor (==2.5.1); extra == "mongodb"
Project-URL: Repository, https://github.com/NEONKID/python-mf-data
